yucebio_yc2_adaptor-2.0.3-py3.9-nspkg.pth
yucebio/yc2/adaptor/__init__.py
yucebio/yc2/adaptor/version.py
yucebio/yc2/adaptor/backend/__init__.py
yucebio/yc2/adaptor/backend/aws.py
yucebio/yc2/adaptor/backend/base.py
yucebio/yc2/adaptor/backend/bcs.py
yucebio/yc2/adaptor/backend/sge.py
yucebio/yc2/adaptor/backend/types.py
yucebio/yc2/adaptor/command/__init__.py
yucebio/yc2/adaptor/command/adaptor.py
yucebio/yc2/adaptor/command/api.py
yucebio/yc2/adaptor/command/base.py
yucebio/yc2/adaptor/command/cromwell.py
yucebio/yc2/adaptor/command/monitor.py
yucebio/yc2/adaptor/util/__init__.py
yucebio/yc2/adaptor/util/api.py
yucebio/yc2/adaptor/util/base_config.py
yucebio/yc2/adaptor/util/config.py
yucebio/yc2/adaptor/util/input_processor.py
yucebio/yc2/adaptor/util/jwt.py
yucebio/yc2/adaptor/util/ldap.py
yucebio/yc2/adaptor/util/monitor.py
yucebio/yc2/adaptor/util/types.py
yucebio/yc2/adaptor/util/wdl_processor.py
yucebio/yc2/adaptor/util/wdl_v1_parser.py
yucebio_yc2_adaptor-2.0.3.dist-info/METADATA
yucebio_yc2_adaptor-2.0.3.dist-info/WHEEL
yucebio_yc2_adaptor-2.0.3.dist-info/entry_points.txt
yucebio_yc2_adaptor-2.0.3.dist-info/namespace_packages.txt
yucebio_yc2_adaptor-2.0.3.dist-info/top_level.txt
yucebio_yc2_adaptor-2.0.3.dist-info/RECORD
