Metadata-Version: 2.1
Name: yucebio-yc2-adaptor
Version: 2.0.3
Summary: Yucebio YC2 WdlAdaptor
Home-page: UNKNOWN
Author: huangqingjun
Author-email: huangqingjun@yucebio.com
License: MIT
Platform: UNKNOWN
Classifier: License :: OSI Approved :: MIT License
Classifier: Programming Language :: Python
Classifier: Programming Language :: Python :: 3
Classifier: Programming Language :: Python :: 3.9
Classifier: Programming Language :: Python :: Implementation :: CPython
Classifier: Programming Language :: Python :: Implementation :: PyPy
Requires-Python: >=3.9
Requires-Dist: json5
Requires-Dist: click
Requires-Dist: requests
Requires-Dist: pymongo
Requires-Dist: batchcompute (>=2.1)
Requires-Dist: PyJWT (~=2.3.0)
Requires-Dist: ldap3 (~=2.9.1)
Requires-Dist: importlib-metadata
Requires-Dist: python-dateutil
